audx/__init__.py
audx/core.py
audx/errors.py
audx/py.typed
audx/utils.py
audx/abi/__init__.py
audx/abi/abi.json
audx/abi/loader.py
audx/asyncio/__init__.py
audx/asyncio/core.py
audx/constants/__init__.py
audx/constants/eip_1967.py
audx/constants/roles.py
audx-0.2.0.dist-info/METADATA
audx-0.2.0.dist-info/WHEEL
audx-0.2.0.dist-info/licenses/LICENSE
audx-0.2.0.dist-info/RECORD
